LICENSE
README.md
README_EN.md
main.py
pyproject.toml
target/release/watchmen
target/release/watchmend
watchmen_rust-0.0.1.dist-info/LICENSE
watchmen_rust-0.0.1.dist-info/METADATA
watchmen_rust-0.0.1.dist-info/WHEEL
watchmen_rust-0.0.1.dist-info/entry_points.txt
watchmen_rust-0.0.1.dist-info/RECORD
