Metadata-Version: 2.1
Name: watchmen-rust
Version: 0.0.1
Summary: Watchmen is a daemon process manager that for you manage and keep your application online 24/7
Home-page: https://docs.ahriknow.com/watchmen
License: Apache-2.0
Keywords: watchmen,ahriknow,daemon,process,manager
Author: ahriknow
Author-email: ahriknow@ahriknow.com
Classifier: License :: OSI Approved :: Apache Software License
Classifier: Programming Language :: Python :: 2
Classifier: Programming Language :: Python :: 2.7
Classifier: Programming Language :: Python :: 3
Classifier: Programming Language :: Python :: 3.4
Classifier: Programming Language :: Python :: 3.5
Classifier: Programming Language :: Python :: 3.6
Classifier: Programming Language :: Python :: 3.7
Classifier: Programming Language :: Python :: 3.8
Classifier: Programming Language :: Python :: 3.9
Classifier: Programming Language :: Python :: 3.10
Classifier: Programming Language :: Python :: 3.11
Classifier: Programming Language :: Python :: 3.12
Project-URL: Repository, https://github.com/ahriroot/watchmen.git
